setup.py
damn/__init__.py
damn/main.py
damn_py.egg-info/PKG-INFO
damn_py.egg-info/SOURCES.txt
damn_py.egg-info/dependency_links.txt
damn_py.egg-info/requires.txt
damn_py.egg-info/top_level.txt
tests/__init__.py
tests/test_damn.py