Metadata-Version: 1.0
Name: damn-py
Version: 0.1
Summary: Directory And Markup Nesting
Home-page: http://github.com/linked/damn-py
Author: Leeward Bound
Author-email: l@lwb.co
License: GPL2
Keywords: damn markup yaml
Platform: UNKNOWN
